{"number":25,"verses":[{"text":"También estos son proverbios de Salomón, los cuales copiaron los varones de Ezequías, rey de Judá:","id":"25:1"},{"text":"Gloria de Dios es encubrir un asunto; Pero honra del rey es escudriñarlo.","id":"25:2"},{"text":"Para la altura de los cielos, y para la profundidad de la tierra, Y para el corazón de los reyes, no hay investigación.","id":"25:3"},{"text":"Quita las escorias de la plata, Y saldrá alhaja al fundidor.","id":"25:4"},{"text":"Aparta al impío de la presencia del rey, Y su trono se afirmará en justicia.","id":"25:5"},{"text":"No te alabes delante del rey, Ni estés en el lugar de los grandes;","id":"25:6"},{"text":"Porque mejor es que se te diga: Sube acá, Y no que seas humillado delante del príncipe A quien han mirado tus ojos.","id":"25:7"},{"text":"No entres apresuradamente en pleito, No sea que no sepas qué hacer al fin, Después que tu prójimo te haya avergonzado.","id":"25:8"},{"text":"Trata tu causa con tu compañero, Y no descubras el secreto a otro,","id":"25:9"},{"text":"No sea que te deshonre el que lo oyere, Y tu infamia no pueda repararse.","id":"25:10"},{"text":"Manzana de oro con figuras de plata Es la palabra dicha como conviene.","id":"25:11"},{"text":"Como zarcillo de oro y joyel de oro fino Es el que reprende al sabio que tiene oído dócil.","id":"25:12"},{"text":"Como frío de nieve en tiempo de la siega, Así es el mensajero fiel a los que lo envían, Pues al alma de su señor da refrigerio.","id":"25:13"},{"text":"Como nubes y vientos sin lluvia, Así es el hombre que se jacta de falsa liberalidad.","id":"25:14"},{"text":"Con larga paciencia se aplaca el príncipe, Y la lengua blanda quebranta los huesos.","id":"25:15"},{"text":"¿Hallaste miel? Come lo que te basta, No sea que hastiado de ella la vomites.","id":"25:16"},{"text":"Detén tu pie de la casa de tu vecino, No sea que hastiado de ti te aborrezca.","id":"25:17"},{"text":"Martillo y cuchillo y saeta aguda Es el hombre que habla contra su prójimo falso testimonio.","id":"25:18"},{"text":"Como diente roto y pie descoyuntado Es la confianza en el prevaricador en tiempo de angustia.","id":"25:19"},{"text":"El que canta canciones al corazón afligido Es como el que quita la ropa en tiempo de frío, o el que sobre el jabón echa vinagre.","id":"25:20"},{"text":"Si el que te aborrece tuviere hambre, dale de comer pan, Y si tuviere sed, dale de beber agua;","id":"25:21"},{"text":"Porque ascuas amontonarás sobre su cabeza, Y Jehová te lo pagará.","id":"25:22"},{"text":"El viento del norte ahuyenta la lluvia, Y el rostro airado la lengua detractora.","id":"25:23"},{"text":"Mejor es estar en un rincón del terrado, Que con mujer rencillosa en casa espaciosa.","id":"25:24"},{"text":"Como el agua fría al alma sedienta, Así son las buenas nuevas de lejanas tierras.","id":"25:25"},{"text":"Como fuente turbia y manantial corrompido, Es el justo que cae delante del impío.","id":"25:26"},{"text":"Comer mucha miel no es bueno, Ni el buscar la propia gloria es gloria.","id":"25:27"},{"text":"Como ciudad derribada y sin muro Es el hombre cuyo espíritu no tiene rienda.","id":"25:28"}]}