{"number":23,"verses":[{"text":"EL SEÑOR es mi pastor; nada me faltará.","id":"23:1"},{"text":"En lugares de delicados pastos me hace yacer: junto a aguas de reposo me lleva.","id":"23:2"},{"text":"Conforta mi alma; me guía por sendas de justicia por amor de su nombre.","id":"23:3"},{"text":"Aunque ande en el valle de la sombra de muerte, no temeré mal alguno; porque tú estás con­migo: tu vara y tu cayado me infunden aliento.","id":"23:4"},{"text":"Aderezas mesa delante de mí en presencia de mis enemigos: unges mi cabeza con aceite: mi copa está rebosando.","id":"23:5"},{"text":"Ciertamente el bien y la mise­ricordia me seguirán todos los días de mi vida: y en la casa del SEÑOR moraré por siempre.","id":"23:6"}]}